swaggerpetstoreopenapi30/__init__.py
swaggerpetstoreopenapi30/api_helper.py
swaggerpetstoreopenapi30/configuration.py
swaggerpetstoreopenapi30/swaggerpetstoreopenapi_30_client.py
swaggerpetstoreopenapi30/controllers/__init__.py
swaggerpetstoreopenapi30/controllers/base_controller.py
swaggerpetstoreopenapi30/controllers/pet_controller.py
swaggerpetstoreopenapi30/controllers/store_controller.py
swaggerpetstoreopenapi30/controllers/user_controller.py
swaggerpetstoreopenapi30/exceptions/__init__.py
swaggerpetstoreopenapi30/exceptions/api_exception.py
swaggerpetstoreopenapi30/http/__init__.py
swaggerpetstoreopenapi30/http/http_call_back.py
swaggerpetstoreopenapi30/http/http_method_enum.py
swaggerpetstoreopenapi30/http/http_request.py
swaggerpetstoreopenapi30/http/http_response.py
swaggerpetstoreopenapi30/http/auth/__init__.py
swaggerpetstoreopenapi30/http/auth/custom_header_authentication.py
swaggerpetstoreopenapi30/models/__init__.py
swaggerpetstoreopenapi30/models/address.py
swaggerpetstoreopenapi30/models/category.py
swaggerpetstoreopenapi30/models/customer.py
swaggerpetstoreopenapi30/models/order.py
swaggerpetstoreopenapi30/models/order_status_enum.py
swaggerpetstoreopenapi30/models/pet.py
swaggerpetstoreopenapi30/models/pet_image.py
swaggerpetstoreopenapi30/models/pet_status_enum.py
swaggerpetstoreopenapi30/models/status_enum.py
swaggerpetstoreopenapi30/models/tag.py
swaggerpetstoreopenapi30/models/user.py
swaggerpetstoreopenapi30/utilities/__init__.py
swaggerpetstoreopenapi30/utilities/file_wrapper.py
sdksio_swagger_petstore_3_sdk-1.0.0.dist-info/LICENSE
sdksio_swagger_petstore_3_sdk-1.0.0.dist-info/METADATA
sdksio_swagger_petstore_3_sdk-1.0.0.dist-info/WHEEL
sdksio_swagger_petstore_3_sdk-1.0.0.dist-info/top_level.txt
sdksio_swagger_petstore_3_sdk-1.0.0.dist-info/RECORD
